odoo9_addon_l10n_es_crm_lead_trade_name-9.0.1.0.0-py2.7-nspkg.pth
odoo9_addon_l10n_es_crm_lead_trade_name-9.0.1.0.0.dist-info/DESCRIPTION.rst
odoo9_addon_l10n_es_crm_lead_trade_name-9.0.1.0.0.dist-info/METADATA
odoo9_addon_l10n_es_crm_lead_trade_name-9.0.1.0.0.dist-info/RECORD
odoo9_addon_l10n_es_crm_lead_trade_name-9.0.1.0.0.dist-info/WHEEL
odoo9_addon_l10n_es_crm_lead_trade_name-9.0.1.0.0.dist-info/metadata.json
odoo9_addon_l10n_es_crm_lead_trade_name-9.0.1.0.0.dist-info/namespace_packages.txt
odoo9_addon_l10n_es_crm_lead_trade_name-9.0.1.0.0.dist-info/top_level.txt
odoo_addons/l10n_es_crm_lead_trade_name/README.rst
odoo_addons/l10n_es_crm_lead_trade_name/__init__.py
odoo_addons/l10n_es_crm_lead_trade_name/__openerp__.py
odoo_addons/l10n_es_crm_lead_trade_name/i18n/bg.po
odoo_addons/l10n_es_crm_lead_trade_name/i18n/ca.po
odoo_addons/l10n_es_crm_lead_trade_name/i18n/es.po
odoo_addons/l10n_es_crm_lead_trade_name/i18n/eu.po
odoo_addons/l10n_es_crm_lead_trade_name/i18n/fr.po
odoo_addons/l10n_es_crm_lead_trade_name/i18n/gl.po
odoo_addons/l10n_es_crm_lead_trade_name/i18n/hr.po
odoo_addons/l10n_es_crm_lead_trade_name/i18n/l10n_es_crm_lead_trade_name.pot
odoo_addons/l10n_es_crm_lead_trade_name/i18n/pt_BR.po
odoo_addons/l10n_es_crm_lead_trade_name/models/__init__.py
odoo_addons/l10n_es_crm_lead_trade_name/models/crm_lead.py
odoo_addons/l10n_es_crm_lead_trade_name/static/description/icon.png
odoo_addons/l10n_es_crm_lead_trade_name/tests/__init__.py
odoo_addons/l10n_es_crm_lead_trade_name/tests/test_lead.py
odoo_addons/l10n_es_crm_lead_trade_name/views/crm_lead.xml
