Metadata-Version: 2.0
Name: odoo9-addon-l10n-es-crm-lead-trade-name
Version: 9.0.1.0.0
Summary: Add trade name field to leads
Home-page: https://github.com/OCA/l10n-spain
Author: Antiun Ingeniería S.L.,QubiQ 2010,Odoo Community Association (OCA)
Author-email: support@odoo-community.org
License: AGPL-3
Platform: UNKNOWN
Classifier: Programming Language :: Python :: 2.7
Classifier: Framework :: Odoo
Classifier: License :: OSI Approved :: GNU Affero General Public License v3
Requires-Dist: odoo (<9.1a,>=9.0a)
Requires-Dist: odoo9-addon-l10n-es-partner
